{"docSchemaVersion":1.0,"id":"66fc0d0a4bb345cc913fc8af","meta":{"actionsByState":{"active":0.0,"fail":0.0,"queued":0.0,"success":0.0},"assets":[],"audit":{"created":{"authProvider":{"id":"","title":"Swimlane"},"date":"2024-10-01T14:54:02.441+00:00","user":{"id":"30598f8a-6519-4d93-84e7-41e8e4e94845","username":"swimlaneadmin@swimlane.com"}},"modified":{"authProvider":{"id":"","title":"Swimlane"},"date":"2024-10-01T14:54:02.441+00:00","user":{"id":"30598f8a-6519-4d93-84e7-41e8e4e94845","username":"swimlaneadmin@swimlane.com"}},"version":1.0},"connectors":[],"enabled":false,"playbooks":[],"pools":[],"sharingUid":"eb32435a-8018-4ef0-bc6e-48e778f32adb","solutionId":"aWNV0vLWoinl_RkR8","src":"schema: playbook/2\nname: solution_aWNV0vLWoinl_RkR8_playbook\nactions:\n  httpRequest_agtpy:\n    title: httpRequest_agtpy\n    type: http\n    description: \"\"\n    on-success: []\n    on-failure: []\n    on-complete: []\n    publish: {}\n    inputs:\n      endpoint: \"\"\n      method: GET\n      headers:\n      - key: \"\"\n        value: \"\"\n        enabled: false\n      queryParameters:\n      - key: \"\"\n        value: \"\"\n        enabled: false\n      pathVariables: []\n      settings:\n        followRedirects: true\n        verifyCertificates: true\n        allowUnsafeLegacyRenegotiation: false\n    pool: $default\n    testInputs:\n      endpoint: https://jsonplaceholder.typicode.com/todos/1\n      method: GET\n      headers:\n      - key: \"\"\n        value: \"\"\n        enabled: false\n      queryParameters:\n      - key: \"\"\n        value: \"\"\n        enabled: false\n      pathVariables: []\n      settings:\n        followRedirects: true\n        verifyCertificates: true\n        allowUnsafeLegacyRenegotiation: false\n    retryUntil:\n      delay: 30000\n      duration: 900000\n      limit: 3\n      if:\n        $:and:\n        - - $:ref: $actions.httpRequest_agtpy.result.status_reason\n          - $:match: ertret\n          - ignoreCase: false\n        - - $:ref: $actions.httpRequest_agtpy.result.body.title\n          - $:match: fggfh\n          - ignoreCase: false\n    meta: {}\n    delay: 0\n    post: {}\n    timeout: 0\n    environment: {}\n    outputSchemaReferenceId: 8875e378-21b3-4117-88c6-83a44b6047fb\nmeta: {}\ntitle: solution_aWNV0vLWoinl_RkR8_playbook\ndescription: \"\"\nnamespace: $default\nentrypoints:\n- httpRequest_agtpy\npool: \"\"\ntimeout: 0\npublish: {}\nenvironment: {}\ninputs:\n  type: object\ntriggers: {}\n","store":{},"validation":{"valid":true}},"playbook":{"actions":{"httpRequest_agtpy":{"meta":{},"title":"httpRequest_agtpy","type":"http","delay":0,"pool":"$default","on-success":[],"on-failure":[],"on-complete":[],"publish":{},"post":{},"timeout":0,"description":"","retryUntil":{"delay":30000,"duration":900000,"if":{"$:and":[[{"$:ref":"$actions.httpRequest_agtpy.result.status_reason"},{"$:match":"ertret"},{"ignoreCase":false}],[{"$:ref":"$actions.httpRequest_agtpy.result.body.title"},{"$:match":"fggfh"},{"ignoreCase":false}]]},"limit":3},"outputSchemaReferenceId":"8875e378-21b3-4117-88c6-83a44b6047fb","asset":"","assetProxy":"","environment":{},"inputs":{"endpoint":"","method":"GET","headers":[{"key":"","value":"","enabled":false}],"queryParameters":[{"key":"","value":"","enabled":false}],"pathVariables":[],"settings":{"followRedirects":true,"verifyCertificates":true,"allowUnsafeLegacyRenegotiation":false}},"testInputs":{"endpoint":"https://jsonplaceholder.typicode.com/todos/1","method":"GET","headers":[{"key":"","value":"","enabled":false}],"queryParameters":[{"key":"","value":"","enabled":false}],"pathVariables":[],"settings":{"followRedirects":true,"verifyCertificates":true,"allowUnsafeLegacyRenegotiation":false}}}},"description":"","entrypoints":["httpRequest_agtpy"],"environment":{},"inputs":{"type":"object"},"meta":{},"name":"solution_aWNV0vLWoinl_RkR8_playbook","namespace":"$default","pool":"","publish":{},"schema":"playbook/2","timeout":0.0,"title":"solution_aWNV0vLWoinl_RkR8_playbook","triggers":{},"uuid":"00000000-0000-0000-0000-000000000000"}}